compas_igs2/__init__.py
compas_igs2/artists/__init__.py
compas_igs2/artists/diagramartist.py
compas_igs2/artists/forceartist.py
compas_igs2/artists/formartist.py
compas_igs2/objects/__init__.py
compas_igs2/objects/diagramobject.py
compas_igs2/objects/forceobject.py
compas_igs2/objects/formobject.py
compas_igs2/rhino/__init__.py
compas_igs2/rhino/install.py
compas_igs2/rhino/register.py
compas_igs2/rhino/artists/__init__.py
compas_igs2/rhino/artists/diagramartist.py
compas_igs2/rhino/artists/forceartist.py
compas_igs2/rhino/artists/formartist.py
compas_igs2/rhino/conduits/__init__.py
compas_igs2/rhino/conduits/forceinspector.py
compas_igs2/rhino/conduits/forminspector.py
compas_igs2/rhino/forms/__init__.py
compas_igs2/rhino/forms/attributesform.py
compas_igs2/rhino/objects/__init__.py
compas_igs2/rhino/objects/diagramobject.py
compas_igs2/rhino/objects/forceobject.py
compas_igs2/rhino/objects/formobject.py
compas_igs2/rhino/ui/__init__.py
compas_igs2/rhino/ui/IGS2/dev/IGS2__toolbar_cmd.py
compas_igs2/rhino/ui/IGS2/dev/IGS2__toolbar_form_assign_forces_cmd.py
compas_igs2/rhino/ui/IGS2/dev/IGS2__toolbar_form_cmd.py
compas_igs2/rhino/ui/IGS2/dev/IGS2__toolbar_form_constraints_edge_cmd.py
compas_igs2/rhino/ui/IGS2/dev/IGS2__toolbar_form_constraints_vertex_cmd.py
compas_igs2/rhino/ui/IGS2/dev/IGS2__toolbar_inspector_cmd.py
compas_igs2/rhino/ui/IGS2/dev/IGS2_constraint_table_cmd.py
compas_igs2/rhino/ui/IGS2/dev/IGS2_docs_cmd.py
compas_igs2/rhino/ui/IGS2/dev/IGS2_edge_information_cmd.py
compas_igs2/rhino/ui/IGS2/dev/IGS2_edges_table_cmd.py
compas_igs2/rhino/ui/IGS2/dev/IGS2_force_constraint_vertex_cmd.py
compas_igs2/rhino/ui/IGS2/dev/IGS2_force_displaysettings_cmd.py
compas_igs2/rhino/ui/IGS2/dev/IGS2_force_from_form_cmd.py
compas_igs2/rhino/ui/IGS2/dev/IGS2_force_inspector_control_cmd.py
compas_igs2/rhino/ui/IGS2/dev/IGS2_force_inspector_off_cmd.py
compas_igs2/rhino/ui/IGS2/dev/IGS2_force_inspector_on_cmd.py
compas_igs2/rhino/ui/IGS2/dev/IGS2_force_move_cmd.py
compas_igs2-0.2.1.dist-info/AUTHORS.md
compas_igs2-0.2.1.dist-info/LICENSE
compas_igs2-0.2.1.dist-info/METADATA
compas_igs2-0.2.1.dist-info/WHEEL
compas_igs2-0.2.1.dist-info/top_level.txt
compas_igs2-0.2.1.dist-info/RECORD
